hhelper/__init__.py
hhelper/helpers/__init__.py
hhelper/helpers/align_posting.py
hhelper/helpers/backup.py
hhelper/helpers/check_valid_journal.py
hhelper/helpers/clean_up_journal.py
hhelper/helpers/clear_tx.py
hhelper/helpers/fetch_price.py
hhelper/helpers/generate_recurring_tx.py
hhelper/helpers/options.py
hhelper/helpers/return_status.py
hhelper/ui/__init__.py
hhelper/ui/display.py
hhelper/ui/menu.py
hhelper/ui/print_greeting.py
hhelper-0.2.0.dist-info/METADATA
hhelper-0.2.0.dist-info/WHEEL
hhelper-0.2.0.dist-info/entry_points.txt
hhelper-0.2.0.dist-info/licenses/LICENSE
hhelper-0.2.0.dist-info/RECORD
