Metadata-Version: 2.4
Name: hhelper
Version: 0.2.0
Summary: Helper Functions for hledger plain text accounting
Author-email: plwg <56353330+plwg@users.noreply.github.com>
License-File: LICENSE
Requires-Python: >=3.9
Requires-Dist: blessed>=1.20.0
Requires-Dist: toml>=0.10.2
Requires-Dist: yfinance>=0.2.61
